cisim/__init__.py
cisim/core.py
cisim/helpers.py
cisim/schemas.py
cisim/stats.py
cisim-1.0.9.1.dist-info/LICENSE
cisim-1.0.9.1.dist-info/METADATA
cisim-1.0.9.1.dist-info/WHEEL
cisim-1.0.9.1.dist-info/top_level.txt
cisim-1.0.9.1.dist-info/RECORD
